trolskgen/__init__.py
trolskgen/ast_types.py
trolskgen/converters.py
trolskgen/core.py
trolskgen/py.typed
trolskgen/templates.py
trolskgen-0.0.20.dist-info/licenses/LICENCE
trolskgen-0.0.20.dist-info/METADATA
trolskgen-0.0.20.dist-info/WHEEL
trolskgen-0.0.20.dist-info/top_level.txt
trolskgen-0.0.20.dist-info/RECORD
