Metadata-Version: 2.4
Name: trolskgen
Version: 0.0.20
Summary: Cute Python codegen
Author-email: Oliver Russell <ojhrussell@gmail.com>
Maintainer-email: Oliver Russell <ojhrussell@gmail.com>
License-Expression: MIT
Project-URL: homepage, https://github.com/leontrolski/trolskgen
Keywords: codegen
Classifier: Programming Language :: Python
Requires-Python: >=3.12
License-File: LICENCE
Requires-Dist: typing-extensions>=4.10.0
Provides-Extra: dev
Requires-Dist: pytest==8.3.5; extra == "dev"
Requires-Dist: ruff==0.11.2; extra == "dev"
Requires-Dist: mypy==1.15.0; extra == "dev"
Requires-Dist: rich==14.0.0; extra == "dev"
Requires-Dist: pydantic==2.11.7; extra == "dev"
Dynamic: license-file
